django_environ_settings.py
django_environ_settings-0.1.2.dist-info/LICENSE
django_environ_settings-0.1.2.dist-info/METADATA
django_environ_settings-0.1.2.dist-info/WHEEL
django_environ_settings-0.1.2.dist-info/top_level.txt
django_environ_settings-0.1.2.dist-info/RECORD
