Metadata-Version: 2.1
Name: django-environ-settings
Version: 0.1.2
Summary: 从环境变量中加载Django配置项。
Author: Tang Bo
Maintainer: Tang Bo
License: Apache License, Version 2.0
Keywords: django
Classifier: Development Status :: 5 - Production/Stable
Classifier: Intended Audience :: Developers
Classifier: Topic :: Software Development :: Libraries :: Python Modules
Classifier: License :: OSI Approved :: Apache Software License
Classifier: Programming Language :: Python :: 3
Classifier: Programming Language :: Python :: 3 :: Only
License-File: LICENSE
Requires-Dist: PyYAML
